crypto_cloud_py/__init__.py
crypto_cloud_py/crypto_cloud_api.py
crypto_cloud_py/crypto_cloud_currency.py
crypto_cloud_py/crypto_cloud_invoice_created.py
crypto_cloud_py/crypto_cloud_invoice_info.py
crypto_cloud_py/crypto_cloud_network.py
crypto_cloud_py/crypto_cloud_project.py
crypto_cloud_py/crypto_cloud_stats.py
crypto_cloud_py/crypto_cloud_stats_amount.py
crypto_cloud_py/crypto_cloud_stats_count.py
crypto_cloud_py/example/__init__.py
crypto_cloud_py/example/main_example.py
crypto_cloud_py-0.2.dist-info/LICENSE.txt
crypto_cloud_py-0.2.dist-info/METADATA
crypto_cloud_py-0.2.dist-info/WHEEL
crypto_cloud_py-0.2.dist-info/top_level.txt
crypto_cloud_py-0.2.dist-info/RECORD
