Metadata-Version: 2.1
Name: crypto-cloud-py
Version: 0.2
Summary: Python client for CryptoCloud API
Home-page: https://github.com/jpleorx/crypto-cloud-py
Author: Leo Ertuna
Author-email: leo.ertuna@gmail.com
License: Creative Commons Attribution-NonCommercial-NoDerivatives 4.0 International Public License
Download-URL: https://pypi.org/project/crypto-cloud-py/
Platform: UNKNOWN
License-File: LICENSE.txt
Requires-Dist: requests
Requires-Dist: pydantic
